Workbook

Sheet Assumptions
A1: GigLedger — Model Assumptions
A3: MARKET & PRICING
A4: Gig workforce (M, 2026) | B4: 58 | C4: BLS / Statista
A5: Basic tier price ($/mo) | B5: 14.99 | C5: Proposal — $14.99
A6: Pro tier price ($/mo) | B6: 28.99 | C6: Proposal — $28.99
A7: Basic tier user mix | B7: 0.6 | C7: 60% of users on Basic
A8: Pro tier user mix | B8: 0.4 | C8: 40% of users on Pro
A10: USER GROWTH
A11: Base users Y1 (K) | B11: 14 | C11: ~0.024% TAM penetration
A12: Y1→Y2 growth rate | B12: 2 | C12: 3x YoY early stage
A13: Y2→Y3 growth rate | B13: 1.12 | C13: 2.1x
A14: Y3→Y4 growth rate | B14: 0.8 | C14: 1.8x
A15: Y4→Y5 growth rate | B15: 0.56 | C15: 1.56x
A16: Bear case multiplier | B16: 0.5 | C16: 50% of Base users
A17: Bull case multiplier | B17: 1.65 | C17: 165% of Base users
A19: COST STRUCTURE
A20: Fixed OpEx Y1 ($MM) | B20: 8.2 | C20: Tech, compliance, team
A21: Fixed OpEx growth rate | B21: 0.2 | C21: 20% annual increase
A22: COGS as % of revenue | B22: 0.28 | C22: BaaS fees, payment rails
A23: CAPEX Y1 ($MM) | B23: 1.5 | C23: Platform build-out
A24: CAPEX growth rate | B24: 0.1 | C24: 10% annual increase
A25: NWC as % of revenue | B25: 0.02 | C25: Digital-first, low NWC
A27: VALUATION INPUTS
A28: Risk-Free Rate (Rf) | B28: 0.045 | C28: 10-yr Treasury — April 2026
A29: Market Risk Premium | B29: 0.0433 | C29: Damodaran USA ERP
A30: Beta (unlevered) | B30: 1.75 | C30: Peer avg 1.52 + 0.23 adj
A31: Tax Rate | B31: 0.21 | C31: US corporate rate
A32: Terminal Growth Rate | B32: 0.04 | C32: Gig economy industry growth
A33: Series A Raise ($MM) | B33: 15 | C33: Funding ask
A34: Pre-Money Valuation ($MM) | B34: 45 | C34: DCF-derived

Sheet Revenue Model
A1: GigLedger — Revenue Model (Base Case)
A2: Metric | B2: 2026 | C2: 2027 | D2: 2028 | E2: 2029 | F2: 2030
A3: USER GROWTH
A4: Base Users (K) | B4: =Assumptions!B11 -> 14 | C4: =B4*(1+Assumptions!B12) -> 42 | D4: =C4*(1+Assumptions!B13) -> 89.04 | E4: =D4*(1+Assumptions!B14) -> 160.272 | F4: =E4*(1+Assumptions!B15) -> 250.02432
A5: Bear Users (K) | B5: =B4*Assumptions!B16 -> 7 | C5: =C4*Assumptions!$B$16 -> 21 | D5: =D4*Assumptions!$B$16 -> 44.52 | E5: =E4*Assumptions!$B$16 -> 80.136 | F5: =F4*Assumptions!$B$16 -> 125.01216
A6: Bull Users (K) | B6: =B4*Assumptions!B17 -> 23.1 | C6: =C4*Assumptions!$B$17 -> 69.3 | D6: =D4*Assumptions!$B$17 -> 146.916 | E6: =E4*Assumptions!$B$17 -> 264.4488 | F6: =F4*Assumptions!$B$17 -> 412.54013
A8: ARPU CALCULATION
A9: Basic ARPU ($/yr) | B9: =Assumptions!B5*12 -> 179.88 | C9: =Assumptions!B5*12 -> 179.88 | D9: =Assumptions!B5*12 -> 179.88 | E9: =Assumptions!B5*12 -> 179.88 | F9: =Assumptions!B5*12 -> 179.88
A10: Pro ARPU ($/yr) | B10: =Assumptions!B6*12 -> 347.88 | C10: =Assumptions!B6*12 -> 347.88 | D10: =Assumptions!B6*12 -> 347.88 | E10: =Assumptions!B6*12 -> 347.88 | F10: =Assumptions!B6*12 -> 347.88
A11: Blended ARPU ($/yr) | B11: =B9*Assumptions!$B$7+B10*Assumptions!$B$8 -> 247.08 | C11: =C9*Assumptions!$B$7+C10*Assumptions!$B$8 -> 247.08 | D11: =D9*Assumptions!$B$7+D10*Assumptions!$B$8 -> 247.08 | E11: =E9*Assumptions!$B$7+E10*Assumptions!$B$8 -> 247.08 | F11: =F9*Assumptions!$B$7+F10*Assumptions!$B$8 -> 247.08
A13: BASE CASE REVENUE ($MM)
A14: Subscription Revenue | B14: =B4*B11/1000 -> 3.45912 | C14: =C4*C11/1000 -> 10.37736 | D14: =D4*D11/1000 -> 22.000003 | E14: =E4*E11/1000 -> 39.600006 | F14: =F4*F11/1000 -> 61.776009
A15: InvoiceNow Financing Fees | B15: =B14*0.18 -> 0.6226416 | C15: =C14*0.18 -> 1.8679248 | D15: =D14*0.18 -> 3.9600006 | E15: =E14*0.18 -> 7.128001 | F15: =F14*0.18 -> 11.119682
A16: IncomeFlow Bridge Fees | B16: =B14*0.12 -> 0.4150944 | C16: =C14*0.12 -> 1.2452832 | D16: =D14*0.12 -> 2.6400004 | E16: =E14*0.12 -> 4.7520007 | F16: =F14*0.12 -> 7.4131211
A17: Total Revenue — Base ($MM) | B17: =SUM(B14:B16) -> 4.496856 | C17: =SUM(C14:C16) -> 13.490568 | D17: =SUM(D14:D16) -> 28.600004 | E17: =SUM(E14:E16) -> 51.480007 | F17: =SUM(F14:F16) -> 80.308812
A19: BEAR CASE REVENUE ($MM)
A20: Bear Subscription Revenue | B20: =B5*B11/1000 -> 1.72956 | C20: =C5*C11/1000 -> 5.18868 | D20: =D5*D11/1000 -> 11.000002 | E20: =E5*E11/1000 -> 19.800003 | F20: =F5*F11/1000 -> 30.888004
A21: Bear Financing Fees | B21: =B20*0.18 -> 0.3113208 | C21: =C20*0.18 -> 0.9339624 | D21: =D20*0.18 -> 1.9800003 | E21: =E20*0.18 -> 3.5640005 | F21: =F20*0.18 -> 5.5598408
A22: Bear Bridge Fees | B22: =B20*0.12 -> 0.2075472 | C22: =C20*0.12 -> 0.6226416 | D22: =D20*0.12 -> 1.3200002 | E22: =E20*0.12 -> 2.3760003 | F22: =F20*0.12 -> 3.7065605
A23: Total Revenue — Bear ($MM) | B23: =SUM(B20:B22) -> 2.248428 | C23: =SUM(C20:C22) -> 6.745284 | D23: =SUM(D20:D22) -> 14.300002 | E23: =SUM(E20:E22) -> 25.740004 | F23: =SUM(F20:F22) -> 40.154406
A25: BULL CASE REVENUE ($MM)
A26: Bull Subscription Revenue | B26: =B6*B11/1000 -> 5.707548 | C26: =C6*C11/1000 -> 17.122644 | D26: =D6*D11/1000 -> 36.300005 | E26: =E6*E11/1000 -> 65.34001 | F26: =F6*F11/1000 -> 101.93041
A27: Bull Financing Fees | B27: =B26*0.18 -> 1.0273586 | C27: =C26*0.18 -> 3.0820759 | D27: =D26*0.18 -> 6.534001 | E27: =E26*0.18 -> 11.761202 | F27: =F26*0.18 -> 18.347475
A28: Bull Bridge Fees | B28: =B26*0.12 -> 0.68490576 | C28: =C26*0.12 -> 2.0547173 | D28: =D26*0.12 -> 4.3560006 | E28: =E26*0.12 -> 7.8408011 | F28: =F26*0.12 -> 12.23165
A29: Total Revenue — Bull ($MM) | B29: =SUM(B26:B28) -> 7.4198124 | C29: =SUM(C26:C28) -> 22.259437 | D29: =SUM(D26:D28) -> 47.190007 | E29: =SUM(E26:E28) -> 84.942012 | F29: =SUM(F26:F28) -> 132.50954

Sheet DCF Model
A1: GigLedger — DCF Valuation Model
A2: Line Item ($MM) | B2: 2026 | C2: 2027 | D2: 2028 | E2: 2029 | F2: 2030
A3: INCOME STATEMENT
A4: Total Revenue | B4: ='Revenue Model'!B17 -> 4.496856 | C4: ='Revenue Model'!C17 -> 13.490568 | D4: ='Revenue Model'!D17 -> 28.600004 | E4: ='Revenue Model'!E17 -> 51.480007 | F4: ='Revenue Model'!F17 -> 80.308812
A5: COGS | B5: =B4*Assumptions!$B$22 -> 1.2591197 | C5: =C4*Assumptions!$B$22 -> 3.777359 | D5: =D4*Assumptions!$B$22 -> 8.0080012 | E5: =E4*Assumptions!$B$22 -> 14.414402 | F5: =F4*Assumptions!$B$22 -> 22.486467
A6: Gross Profit | B6: =B4-B5 -> 3.2377363 | C6: =C4-C5 -> 9.713209 | D6: =D4-D5 -> 20.592003 | E6: =E4-E5 -> 37.065605 | F6: =F4-F5 -> 57.822344
A7: Gross Margin % | B7: =IF(B4=0,0,B6/B4) -> 0.72 | C7: =IF(C4=0,0,C6/C4) -> 0.72 | D7: =IF(D4=0,0,D6/D4) -> 0.72 | E7: =IF(E4=0,0,E6/E4) -> 0.72 | F7: =IF(F4=0,0,F6/F4) -> 0.72
A8: Fixed Operating Expenses | B8: =Assumptions!B20 -> 8.2 | C8: =B8*(1+Assumptions!$B$21) -> 9.84 | D8: =C8*(1+Assumptions!$B$21) -> 11.808 | E8: =D8*(1+Assumptions!$B$21) -> 14.1696 | F8: =E8*(1+Assumptions!$B$21) -> 17.00352
A9: EBITDA | B9: =B6-B8 -> -4.9622637 | C9: =C6-C8 -> -0.12679104 | D9: =D6-D8 -> 8.784003 | E9: =E6-E8 -> 22.896005 | F9: =F6-F8 -> 40.818824
A10: EBITDA Margin % | B10: =IF(B4=0,0,B9/B4) -> -1.1034962 | C10: =IF(C4=0,0,C9/C4) -> -0.0093984953 | D10: =IF(D4=0,0,D9/D4) -> 0.30713293 | E10: =IF(E4=0,0,E9/E4) -> 0.44475528 | F10: =IF(F4=0,0,F9/F4) -> 0.5082733
A11: D&A (est. 5% of revenue) | B11: =B4*0.05 -> 0.2248428 | C11: =C4*0.05 -> 0.6745284 | D11: =D4*0.05 -> 1.4300002 | E11: =E4*0.05 -> 2.5740004 | F11: =F4*0.05 -> 4.0154406
A12: EBIT | B12: =B9-B11 -> -5.1871065 | C12: =C9-C11 -> -0.80131944 | D12: =D9-D11 -> 7.3540028 | E12: =E9-E11 -> 20.322005 | F12: =F9-F11 -> 36.803384
A13: Taxes (21%) | B13: =MAX(0,B12*Assumptions!$B$31) -> 0 | C13: =MAX(0,C12*Assumptions!$B$31) -> 0 | D13: =MAX(0,D12*Assumptions!$B$31) -> 1.5443406 | E13: =MAX(0,E12*Assumptions!$B$31) -> 4.2676211 | F13: =MAX(0,F12*Assumptions!$B$31) -> 7.7287106
A14: NOPAT | B14: =B12-B13 -> -5.1871065 | C14: =C12-C13 -> -0.80131944 | D14: =D12-D13 -> 5.8096622 | E14: =E12-E13 -> 16.054384 | F14: =F12-F13 -> 29.074673
A16: FREE CASH FLOW
A17: NOPAT | B17: =B14 -> -5.1871065 | C17: =C14 -> -0.80131944 | D17: =D14 -> 5.8096622 | E17: =E14 -> 16.054384 | F17: =F14 -> 29.074673
A18: Add back D&A | B18: =B11 -> 0.2248428 | C18: =C11 -> 0.6745284 | D18: =D11 -> 1.4300002 | E18: =E11 -> 2.5740004 | F18: =F11 -> 4.0154406
A19: Less CAPEX | B19: =Assumptions!B23 -> 1.5 | C19: =B19*(1+Assumptions!$B$24) -> 1.65 | D19: =C19*(1+Assumptions!$B$24) -> 1.815 | E19: =D19*(1+Assumptions!$B$24) -> 1.9965 | F19: =E19*(1+Assumptions!$B$24) -> 2.19615
A20: Less Change in NWC | B20: =B4*Assumptions!$B$25 -> 0.08993712 | C20: =C4*Assumptions!$B$25 -> 0.26981136 | D20: =D4*Assumptions!$B$25 -> 0.57200008 | E20: =E4*Assumptions!$B$25 -> 1.0296001 | F20: =F4*Assumptions!$B$25 -> 1.6061762
A21: Free Cash Flow (FCFF) | B21: =B17+B18-B19-B20 -> -6.5522008 | C21: =C17+C18-C19-C20 -> -2.0466024 | D21: =D17+D18-D19-D20 -> 4.8526623 | E21: =E17+E18-E19-E20 -> 15.602284 | F21: =F17+F18-F19-F20 -> 29.287788
A23: DCF VALUATION
A24: WACC | B24: =Assumptions!B28+Assumptions!B30*Assumptions!B29 -> 0.120775 | C24: =Assumptions!B28+Assumptions!B30*Assumptions!B29 -> 0.120775 | D24: =Assumptions!B28+Assumptions!B30*Assumptions!B29 -> 0.120775 | E24: =Assumptions!B28+Assumptions!B30*Assumptions!B29 -> 0.120775 | F24: =Assumptions!B28+Assumptions!B30*Assumptions!B29 -> 0.120775
A25: Period (n) | B25: 1 | C25: 2 | D25: 3 | E25: 4 | F25: 5
A26: Discount Factor | B26: =1/(1+B24)^B25 -> 0.89223974 | C26: =1/(1+C24)^C25 -> 0.79609176 | D26: =1/(1+D24)^D25 -> 0.71030471 | E26: =1/(1+E24)^E25 -> 0.63376209 | F26: =1/(1+F24)^F25 -> 0.56546773
A27: PV of FCF | B27: =B21*B26 -> -5.846134 | C27: =C21*C26 -> -1.6292833 | D27: =D21*D26 -> 3.4468689 | E27: =E21*E26 -> 9.8881363 | F27: =F21*F26 -> 16.561299
A29: TERMINAL VALUE & SUMMARY
A30: Sum of PV(FCF) | B30: =SUM(B27:F27) -> 22.420887
A31: Terminal FCF (Y5 × (1+g)) | B31: =F21*(1+Assumptions!B32) -> 30.459299
A32: Terminal Value (TV) | B32: =B31/(B24-Assumptions!B32) -> 377.0882
A33: PV of Terminal Value | B33: =B32/(1+B24)^5 -> 213.23121
A34: Enterprise Value ($MM) | B34: =B30+B33 -> 235.65209
A35: Pre-Money Valuation ($MM) | B35: =Assumptions!B34 -> 45
A36: Series A Raise ($MM) | B36: =Assumptions!B33 -> 15
A37: Post-Money Valuation ($MM) | B37: =B35+B36 -> 60
A38: Implied Ownership % | B38: =B36/B37 -> 0.25

Sheet Beta Calculation
A1: GigLedger — Top-Down Beta Calculation (Peer Group)
A2: Company | B2: MVE ($B) | C2: EV ($B) | D2: D/E Ratio | E2: Tax Rate | F2: Levered Beta | G2: Unlevered Beta
A3: Intuit (INTU) | B3: 168 | C3: 174 | D3: 0.25 | E3: 0.21 | F3: 1.25 | G3: =F3/(1+(1-E3)*D3) -> 1.0438413
A4: Block (SQ) | B4: 40 | C4: 38 | D4: 0.35 | E4: 0.21 | F4: 2.15 | G4: =F4/(1+(1-E4)*D4) -> 1.684293
A5: PayPal (PYPL) | B5: 68 | C5: 71 | D5: 0.28 | E5: 0.21 | F5: 1.4 | G5: =F5/(1+(1-E5)*D5) -> 1.1464134
A6: Robinhood (HOOD) | B6: 22 | C6: 20 | D6: 0.08 | E6: 0.21 | F6: 2.3 | G6: =F6/(1+(1-E6)*D6) -> 2.1632807
A7: Average Unlevered Beta | G7: =AVERAGE(G3:G6) -> 1.5094571
A8: Applied Beta (GigLedger) | G8: =Assumptions!B30 -> 1.75
A10: Note: Unlevered Beta = Levered Beta / (1 + (1 − Tax Rate) × D/E). Early-stage startup premium of +0.23 applied.
A11: Sources: SEC 10-K Annual Filings (Intuit, Block, PayPal, Robinhood), YCharts, Damodaran Online — April 2026

Sheet WACC
A1: GigLedger — WACC & Cost of Capital
A3: CAPM CALCULATION
A4: Risk-Free Rate (Rf) | B4: =Assumptions!B28 -> 0.045 | C4: 10-yr US Treasury — April 2026
A5: Market Risk Premium (MRP) | B5: =Assumptions!B29 -> 0.0433 | C5: Damodaran USA Equity Risk Premium
A6: Beta (unlevered, applied) | B6: =Assumptions!B30 -> 1.75 | C6: Peer avg 1.52 + startup adj. 0.23
A7: Cost of Equity (CAPM) | B7: =B4+B6*B5 -> 0.120775 | C7: Rf + β × MRP
A8: WACC (all-equity, no debt) | B8: =B7 -> 0.120775 | C8: Early-stage: assume no debt financing
A10: DAMODARAN CROSS-CHECK
A11: FinTech / Online Services | B11: 0.105 | C11: Damodaran sector WACC — April 2026
A12: Software (Internet) | B12: 0.118 | C12: Damodaran sector WACC — April 2026
A13: Financial Services (Banks) | B13: 0.082 | C13: Damodaran sector WACC — April 2026
A14: GigLedger Applied WACC | B14: =B8 -> 0.120775 | C14: Our CAPM derivation
A16: TERMINAL VALUE INPUTS
A17: Terminal Growth Rate | B17: =Assumptions!B32 -> 0.04 | C17: Long-run gig economy growth
A18: Projection Horizon (yrs) | B18: 5 | C18: Rapid growth phase
A19: FCF Positive From (Year) | B19: 4 | C19: 2029 base case
A21: Formula: Cost of Equity = Rf + β × MRP = 4.50% + 1.75 × 4.33% = 12.08% → WACC = 12.1%
A22: Sources: US Treasury (treasury.gov), Damodaran Online (pages.stern.nyu.edu/~adamodar/) — April 2026

Sheet Cap Table
A1: GigLedger — Capitalization Table
A2: Shareholder | B2: Pre Shares | C2: Pre-Money % | D2: New Shares | E2: Post Shares | F2: Post-Money %
A3: Founders (combined) | B3: 7500 | C3: =B3/SUM($B$3:$B$5) -> 0.75 | D3: 0 | E3: =B3+D3 -> 7500 | F3: =E3/SUM($E$3:$E$5) -> 0.56251406
A4: Employee Option Pool | B4: 2500 | C4: =B4/SUM($B$3:$B$5) -> 0.25 | D4: 0 | E4: =B4+D4 -> 2500 | F4: =E4/SUM($E$3:$E$5) -> 0.18750469
A5: Series A Investors | B5: 0 | C5: =B5/SUM($B$3:$B$5) -> 0 | D5: 3333 | E5: =B5+D5 -> 3333 | F5: =E5/SUM($E$3:$E$5) -> 0.24998125
A6: TOTAL | B6: =SUM(B3:B5) -> 10000 | C6: =SUM(C3:C5) -> 1 | D6: =SUM(D3:D5) -> 3333 | E6: =SUM(E3:E5) -> 13333 | F6: =SUM(F3:F5) -> 1
A8: KEY METRICS
A9: Pre-Money Valuation ($MM) | B9: =Assumptions!B34 -> 45 | C9: DCF-derived
A10: Series A Raise ($MM) | B10: =Assumptions!B33 -> 15 | C10: Funding ask
A11: Post-Money Valuation ($MM) | B11: =Assumptions!B34+Assumptions!B33 -> 60 | C11: Pre + Raise
A12: Price per Share ($) | B12: =B9*1000000/SUM(E3:E5) -> 3375.0844 | C12: Post-money / total shares
A13: Series A Ownership % | B13: =D5/SUM(E3:E5) -> 0.24998125 | C13: Investor implied stake
