Workbook

Sheet Summary
A1: WALMART INC. (WMT) | G1: EQUITY RESEARCH | INITIATING COVERAGE
A2: Consumer Staples / Mass Merchandise Retail | NYSE: WMT | G2: April 2026 | Prices as of report date
A4: OVERWEIGHT | C4: Price Target | D4: ='DCF Valuation'!C29*0.7+'Trading Comps'!B31*0.3 -> 97.106508 | F4: Current Price (verify) | G4: 95 | H4: Implied Upside | I4: =(D4-G4)/G4 -> 0.022173765 | K4: 52-Wk Range (verify) | L4: $58 - $105
A6: INVESTMENT THESIS
A7: 1. Margin Expansion Underpriced
A8: Walmart Connect (advertising), Walmart+, and fulfillment services are structurally higher-margin than core retail. We project operating margin expanding from 4.2% in FY2026 to 6.2% by FY2031. Consensus sits at 4.8%. That 140bps gap is the core variant view.
A9: 2. Advertising Is the Real Story
A10: Walmart Connect is a $3-4B revenue business growing 20-30% per year at ~70% gross margins. Every incremental dollar of ad revenue is worth 15x more to operating income than a dollar of grocery revenue. Most models do not break this out separately.
A11: 3. Capex Cycle Is Peaking
A12: Fulfillment capex has been rising from 2% to 3.7% of revenue. We model it peaking in FY2027E and declining to 3.0% by FY2031E. That alone adds $5B+ to annual FCF. The market is pricing in permanent capex intensity, not a peak.
A14: FINANCIAL SUMMARY ($mm)
A15: Metric | B15: FY2024A | C15: FY2025A | D15: FY2026A | F15: FY2027E | G15: FY2028E | H15: FY2029E | I15: FY2030E | K15: FY2031E
A16: Revenue | B16: ='Income Statement'!F4 -> 648125 | C16: ='Income Statement'!G4 -> 680985 | D16: ='Income Statement'!H4 -> 713163 | F16: ='Income Statement'!I4 -> 745255.33 | G16: ='Income Statement'!J4 -> 778791.83 | H16: ='Income Statement'!K4 -> 812279.87 | I16: ='Income Statement'!L4 -> 844771.07 | J16: ='Income Statement'!M4 -> 876872.37
A17: Gross Profit | B17: ='Income Statement'!F6 -> 157983 | C17: ='Income Statement'!G6 -> 169232 | D17: ='Income Statement'!H6 -> 177768 | F17: ='Income Statement'!I6 -> 187059.09 | G17: ='Income Statement'!J6 -> 197034.33 | H17: ='Income Statement'!K6 -> 207131.37 | I17: ='Income Statement'!L6 -> 217106.16 | J17: ='Income Statement'!M6 -> 227109.94
A18: Gross Margin % | B18: ='Income Statement'!F7 -> 0.24375391 | C18: ='Income Statement'!G7 -> 0.24851061 | D18: ='Income Statement'!H7 -> 0.249267 | F18: ='Income Statement'!I7 -> 0.251 | G18: ='Income Statement'!J7 -> 0.253 | H18: ='Income Statement'!K7 -> 0.255 | I18: ='Income Statement'!L7 -> 0.257 | J18: ='Income Statement'!M7 -> 0.259
A19: Operating Income | B19: ='Income Statement'!F10 -> 27012 | C19: ='Income Statement'!G10 -> 29348 | D19: ='Income Statement'!H10 -> 29825 | F19: ='Income Statement'!I10 -> 34281.745 | G19: ='Income Statement'!J10 -> 38939.591 | H19: ='Income Statement'!K10 -> 43863.113 | I19: ='Income Statement'!L10 -> 48996.722 | J19: ='Income Statement'!M10 -> 54366.087
A20: Op. Margin % | B20: ='Income Statement'!F11 -> 0.041677146 | C20: ='Income Statement'!G11 -> 0.043096397 | D20: ='Income Statement'!H11 -> 0.041820734 | F20: ='Income Statement'!I11 -> 0.046 | G20: ='Income Statement'!J11 -> 0.05 | H20: ='Income Statement'!K11 -> 0.054 | I20: ='Income Statement'!L11 -> 0.058 | J20: ='Income Statement'!M11 -> 0.062
A21: EBITDA | B21: ='Income Statement'!F18 -> 38865 | C21: ='Income Statement'!G18 -> 42321 | D21: ='Income Statement'!H18 -> 44028 | F21: ='Income Statement'!I18 -> 49186.852 | G21: ='Income Statement'!J18 -> 54515.428 | H21: ='Income Statement'!K18 -> 60108.711 | I21: ='Income Statement'!L18 -> 65892.143 | J21: ='Income Statement'!M18 -> 71903.534
A22: EBITDA Margin % | B22: ='Income Statement'!F19 -> 0.059965284 | C22: ='Income Statement'!G19 -> 0.062146743 | D22: ='Income Statement'!H19 -> 0.061736237 | F22: ='Income Statement'!I19 -> 0.066 | G22: ='Income Statement'!J19 -> 0.07 | H22: ='Income Statement'!K19 -> 0.074 | I22: ='Income Statement'!L19 -> 0.078 | J22: ='Income Statement'!M19 -> 0.082
A23: Net Income | B23: ='Income Statement'!F16 -> 16270 | C23: ='Income Statement'!G16 -> 20157 | D23: ='Income Statement'!H16 -> 22270 | F23: ='Income Statement'!I16 -> 25444.309 | G23: ='Income Statement'!J16 -> 28937.693 | H23: ='Income Statement'!K16 -> 32630.335 | I23: ='Income Statement'!L16 -> 36480.541 | J23: ='Income Statement'!M16 -> 40507.565
A24: EPS (Diluted) | B24: ='Income Statement'!F22 -> 1.91 | C24: ='Income Statement'!G22 -> 2.41 | D24: ='Income Statement'!H22 -> 2.73 | F24: ='Income Statement'!I22 -> 3.200542 | G24: ='Income Statement'!J22 -> 3.6722961 | H24: ='Income Statement'!K22 -> 4.1780198 | I24: ='Income Statement'!L22 -> 4.7132483 | J24: ='Income Statement'!M22 -> 5.2812992
A25: Free Cash Flow | B25: ='Cash Flow Statement'!F26 -> 15370 | C25: ='Cash Flow Statement'!G26 -> 13092 | D25: ='Cash Flow Statement'!H26 -> 15029 | F25: ='Cash Flow Statement'!I26 -> 13647.596 | G25: ='Cash Flow Statement'!J26 -> 17366.42 | H25: ='Cash Flow Statement'!K26 -> 22164.557 | I25: ='Cash Flow Statement'!L26 -> 27265.674 | J25: ='Cash Flow Statement'!M26 -> 32677.278
A27: VALUATION SUMMARY
A28: DCF Price Target (7.0% WACC, 16x Exit) | D28: ='DCF Valuation'!C29 -> 110.7029 | E28: Weight: 70%
A29: Comps Price Target (50% EV/EBITDA, 50% P/E) | D29: ='Trading Comps'!B31 -> 65.381589 | E29: Weight: 30%
A30: BLENDED PRICE TARGET (70% DCF / 30% Comps) | D30: ='DCF Valuation'!C29*0.7+'Trading Comps'!B31*0.3 -> 97.106508 | F30: Current Price (update manually): | I30: =G4 -> 95
A32: KEY CATALYSTS | H32: KEY RISKS
A33: 1. Walmart Connect revenue crossing $5B milestone (FY2027E) | H33: 1. Amazon accelerates grocery/retail investment, compressing Walmart's pricing power
A34: 2. Walmart+ subscriber count surpassing 50mm (inflection point for recurring rev) | H34: 2. Consumer trade-down reverses as macro improves (reduces Walmart traffic tailwind)
A35: 3. Quarterly earnings showing operating margin above 4.5% for two consecutive quarters | H35: 3. Advertising revenue growth decelerates if brand spend shifts to social media
A36: 4. Announcement of third-party fulfillment monetization (similar to Amazon FBA) | H36: 4. Execution risk on fulfillment buildout: cost overruns or ROI disappointment
A37: 5. Capex guidance reduction signaling peak of investment cycle | H37: 5. Regulatory risk on data usage for Walmart Connect targeting
A39: This report is for educational purposes only. All financial data sourced from Macrotrends / public filings. Comp estimates are approximate and should be verified with current market data prior to any use.

Sheet Income Statement
A1: WALMART INC. (WMT) - Income Statement
A2: USD in millions | Fiscal Year Ends January 31 | Source: Macrotrends
A3: Metric | B3: FY2020 | C3: FY2021 | D3: FY2022 | E3: FY2023 | F3: FY2024 | G3: FY2025 | H3: FY2026 | I3: FY2027E | J3: FY2028E | K3: FY2029E | L3: FY2030E | M3: FY2031E
A4: Revenue | B4: 523964 | C4: 559151 | D4: 572754 | E4: 611289 | F4: 648125 | G4: 680985 | H4: 713163 | I4: =H4*(1+Assumptions!B5) -> 745255.33 | J4: =I4*(1+Assumptions!C5) -> 778791.83 | K4: =J4*(1+Assumptions!D5) -> 812279.87 | L4: =K4*(1+Assumptions!E5) -> 844771.07 | M4: =L4*(1+Assumptions!F5) -> 876872.37
A5: Cost of Goods Sold | B5: 394605 | C5: 420315 | D5: 429000 | E5: 463721 | F5: 490142 | G5: 511753 | H5: 535395 | I5: =I4*(1-Assumptions!B6) -> 558196.25 | J5: =J4*(1-Assumptions!C6) -> 581757.49 | K5: =K4*(1-Assumptions!D6) -> 605148.51 | L5: =L4*(1-Assumptions!E6) -> 627664.9 | M5: =M4*(1-Assumptions!F6) -> 649762.43
A6: Gross Profit | B6: =B4-B5 -> 129359 | C6: =C4-C5 -> 138836 | D6: =D4-D5 -> 143754 | E6: =E4-E5 -> 147568 | F6: =F4-F5 -> 157983 | G6: =G4-G5 -> 169232 | H6: =H4-H5 -> 177768 | I6: =I4-I5 -> 187059.09 | ... M6: =M4-M5 -> 227109.94
A7: Gross Margin % | B7: =B6/B4 -> 0.24688528 | C7: =C6/C4 -> 0.24829787 | D7: =D6/D4 -> 0.25098733 | E7: =E6/E4 -> 0.24140464 | F7: =F6/F4 -> 0.24375391 | G7: =G6/G4 -> 0.24851061 | H7: =H6/H4 -> 0.249267 | I7: =IF(I4=0,0,I6/I4) -> 0.251 | J7: =IF(J4=0,0,J6/J4) -> 0.253 | K7: =IF(K4=0,0,K6/K4) -> 0.255 | L7: =IF(L4=0,0,L6/L4) -> 0.257 | M7: =IF(M4=0,0,M6/M4) -> 0.259
A8: SG&A Expenses | B8: 108791 | C8: 116288 | D8: 117812 | E8: 127140 | F8: 130971 | G8: 139884 | H8: 147943 | I8: =I4*Assumptions!B7 -> 152777.34 | J8: =J4*Assumptions!C7 -> 158094.74 | K8: =K4*Assumptions!D7 -> 163268.25 | L8: =L4*Assumptions!E7 -> 168109.44 | M8: =M4*Assumptions!F7 -> 172743.86
A9: Operating Expenses | B9: =B8 -> 108791 | C9: =C8 -> 116288 | D9: =D8 -> 117812 | E9: =E8 -> 127140 | F9: =F8 -> 130971 | G9: =G8 -> 139884 | H9: =H8 -> 147943 | I9: =I8 -> 152777.34 | ... M9: =M8 -> 172743.86
A10: Operating Income | B10: =B6-B9 -> 20568 | C10: =C6-C9 -> 22548 | D10: =D6-D9 -> 25942 | E10: =E6-E9 -> 20428 | F10: =F6-F9 -> 27012 | G10: =G6-G9 -> 29348 | H10: =H6-H9 -> 29825 | I10: =I6-I9 -> 34281.745 | ... M10: =M6-M9 -> 54366.087
A11: Operating Margin % | B11: =B10/B4 -> 0.039254605 | C11: =C10/C4 -> 0.040325422 | D11: =D10/D4 -> 0.045293442 | E11: =E10/E4 -> 0.033417909 | F11: =F10/F4 -> 0.041677146 | G11: =G10/G4 -> 0.043096397 | H11: =H10/H4 -> 0.041820734 | I11: =IF(I4=0,0,I10/I4) -> 0.046 | J11: =IF(J4=0,0,J10/J4) -> 0.05 | K11: =IF(K4=0,0,K10/K4) -> 0.054 | L11: =IF(L4=0,0,L10/L4) -> 0.058 | M11: =IF(M4=0,0,M10/M4) -> 0.062
A12: Non-Operating Inc/Exp | B12: -452 | C12: -1984 | D12: -7246 | E12: -3412 | F12: -5164 | G12: -3039 | H12: -356 | I12: =Assumptions!B13 -> -356 | J12: =Assumptions!C13 -> -356 | K12: =Assumptions!D13 -> -356 | L12: =Assumptions!E13 -> -356 | M12: =Assumptions!F13 -> -356
A13: Pre-Tax Income | B13: =B10+B12 -> 20116 | C13: =C10+C12 -> 20564 | D13: =D10+D12 -> 18696 | E13: =E10+E12 -> 17016 | F13: =F10+F12 -> 21848 | G13: =G10+G12 -> 26309 | H13: =H10+H12 -> 29469 | I13: =I10+I12 -> 33925.745 | ... M13: =M10+M12 -> 54010.087
A14: Income Taxes | B14: 4915 | C14: 6858 | D14: 4756 | E14: 5724 | F14: 5578 | G14: 6152 | H14: 7199 | I14: =I13*Assumptions!B10 -> 8481.4364 | J14: =J13*Assumptions!C10 -> 9645.8978 | K14: =K13*Assumptions!D10 -> 10876.778 | L14: =L13*Assumptions!E10 -> 12160.18 | M14: =M13*Assumptions!F10 -> 13502.522
A15: Effective Tax Rate | B15: =IF(B13=0,0,B14/B13) -> 0.24433287 | C15: =IF(C13=0,0,C14/C13) -> 0.33349543 | D15: =IF(D13=0,0,D14/D13) -> 0.25438596 | E15: =IF(E13=0,0,E14/E13) -> 0.33638928 | F15: =IF(F13=0,0,F14/F13) -> 0.25530941 | G15: =IF(G13=0,0,G14/G13) -> 0.23383633 | H15: =IF(H13=0,0,H14/H13) -> 0.24429061 | I15: =IF(I13=0,0,I14/I13) -> 0.25 | ... M15: =IF(M13=0,0,M14/M13) -> 0.25
A16: Net Income | B16: =B13-B14 -> 15201 | C16: =C13-C14 -> 13706 | D16: =D13-D14 -> 13940 | E16: =E13-E14 -> 11292 | F16: =F13-F14 -> 16270 | G16: =G13-G14 -> 20157 | H16: =H13-H14 -> 22270 | I16: =I13-I14 -> 25444.309 | ... M16: =M13-M14 -> 40507.565
A17: Net Margin % | B17: =B16/B4 -> 0.029011535 | C17: =C16/C4 -> 0.024512162 | D17: =D16/D4 -> 0.024338547 | E17: =E16/E4 -> 0.018472441 | F17: =F16/F4 -> 0.025103182 | G17: =G16/G4 -> 0.029599771 | H17: =H16/H4 -> 0.031227083 | I17: =IF(I4=0,0,I16/I4) -> 0.034141734 | J17: =IF(J4=0,0,J16/J4) -> 0.037157161 | K17: =IF(K4=0,0,K16/K4) -> 0.040171296 | L17: =IF(L4=0,0,L16/L4) -> 0.043183938 | M17: =IF(M4=0,0,M16/M4) -> 0.046195509
A18: EBITDA | B18: 31555 | C18: 33700 | D18: 36600 | E18: 31373 | F18: 38865 | G18: 42321 | H18: 44028 | I18: =I10+I20 -> 49186.852 | J18: =J10+J20 -> 54515.428 | K18: =K10+K20 -> 60108.711 | L18: =L10+L20 -> 65892.143 | M18: =M10+M20 -> 71903.534
A19: EBITDA Margin % | B19: =B18/B4 -> 0.060223603 | C19: =C18/C4 -> 0.060269945 | D19: =D18/D4 -> 0.06390178 | E19: =E18/E4 -> 0.051322697 | F19: =F18/F4 -> 0.059965284 | G19: =G18/G4 -> 0.062146743 | H19: =H18/H4 -> 0.061736237 | I19: =IF(I4=0,0,I18/I4) -> 0.066 | J19: =IF(J4=0,0,J18/J4) -> 0.07 | K19: =IF(K4=0,0,K18/K4) -> 0.074 | L19: =IF(L4=0,0,L18/L4) -> 0.078 | M19: =IF(M4=0,0,M18/M4) -> 0.082
A20: D&A (from CF) | B20: 10987 | C20: 11152 | D20: 10658 | E20: 10945 | F20: 11853 | G20: 12973 | H20: 14203 | I20: =I4*Assumptions!B12 -> 14905.107 | J20: =J4*Assumptions!C12 -> 15575.837 | K20: =K4*Assumptions!D12 -> 16245.597 | L20: =L4*Assumptions!E12 -> 16895.421 | M20: =M4*Assumptions!F12 -> 17537.447
A21: Shares Outstanding (mm) | B21: 8604 | C21: 8541 | D21: 8415 | E21: 8108 | F21: 8081 | G21: 8041 | H21: 8022 | I21: =Assumptions!B11 -> 7950 | J21: =Assumptions!C11 -> 7880 | K21: =Assumptions!D11 -> 7810 | L21: =Assumptions!E11 -> 7740 | M21: =Assumptions!F11 -> 7670
A22: EPS (Diluted) | B22: 1.73 | C22: 1.58 | D22: 1.62 | E22: 1.42 | F22: 1.91 | G22: 2.41 | H22: 2.73 | I22: =IF(I21=0,0,I16/I21) -> 3.200542 | J22: =IF(J21=0,0,J16/J21) -> 3.6722961 | K22: =IF(K21=0,0,K16/K21) -> 4.1780198 | L22: =IF(L21=0,0,L16/L21) -> 4.7132483 | M22: =IF(M21=0,0,M16/M21) -> 5.2812992
A25: Colors Info: | B25: Blue = Input form website | D25: Black = calculated / formula | F25: Green = Cross-sheet calc

Sheet Balance Sheet
A1: WALMART INC. (WMT) - Balance Sheet
A2: USD in millions | Fiscal Year Ends January 31 | Source: Macrotrends | *They only had until 2025 (we are in 2026)*
A3: Metric | B3: FY2020 | C3: FY2021 | D3: FY2022 | E3: FY2023 | F3: FY2024 | G3: FY2025
A4: ASSETS
A5: Cash & Equivalents | B5: 9465 | C5: 17741 | D5: 14760 | E5: 8625 | F5: 9867 | G5: 9037
A6: Receivables | B6: 6284 | C6: 6516 | D6: 8280 | E6: 7933 | F6: 8796 | G6: 9975
A7: Inventory | B7: 44435 | C7: 44949 | D7: 56511 | E7: 56576 | F7: 54892 | G7: 56435
A8: Pre-Paid Expenses | B8: 1622 | C8: 20861 | D8: 1519 | E8: 2521 | F8: 3322 | G8: 4011
A9: Total Current Assets | B9: 61806 | C9: 90067 | D9: 81070 | E9: 75655 | F9: 76877 | G9: 79458
A10: PP&E, Net | B10: 105208 | C10: 92201 | D10: 94515 | E10: 100760 | F10: 110810 | G10: 119993
A11: Goodwill & Intangibles | B11: 31073 | C11: 28983 | D11: 29014 | E11: 28174 | F11: 28113 | G11: 28792
A12: Other Long-Term Assets | B12: 16567 | C12: 23598 | D12: 22152 | E12: 20134 | F12: 17071 | G12: 12869
A13: Total Long-Term Assets | B13: =B10+B11+B12 -> 152848 | C13: =C10+C11+C12 -> 144782 | D13: =D10+D11+D12 -> 145681 | E13: =E10+E11+E12 -> 149068 | F13: =F10+F11+F12 -> 155994 | G13: =G10+G11+G12 -> 161654
A14: TOTAL ASSETS | B14: 236495 | C14: 252496 | D14: 244860 | E14: 243197 | F14: 252399 | G14: 260823
A15: LIABILITIES
A16: Total Current Liabilities | B16: 77790 | C16: 92645 | D16: 87379 | E16: 92198 | F16: 92415 | G16: 96584
A17: Long-Term Debt | B17: 48021 | C17: 45041 | D17: 39107 | E17: 39492 | F17: 41841 | G17: 39324
A18: Total Long-Term Liabilities | B18: 77153 | C18: 72320 | D18: 65590 | E18: 67245 | F18: 69635 | G18: 66818
A19: TOTAL LIABILITIES | B19: 154943 | C19: 164965 | D19: 152969 | E19: 159443 | F19: 162050 | G19: 163402
A20: EQUITY
A21: Common Stock Net | B21: 284 | C21: 282 | D21: 276 | E21: 808 | F21: 805 | G21: 802
A22: Retained Earnings | B22: 83943 | C22: 88763 | D22: 86904 | E22: 83135 | F22: 89814 | G22: 98313
A23: Comprehensive Income | B23: -12805 | C23: -11766 | D23: -8766 | E23: -11680 | F23: -11302 | G23: -13605
A24: Total Shareholders Equity | B24: 81552 | C24: 87531 | D24: 91891 | E24: 83754 | F24: 90349 | G24: 97421
A25: TOTAL LIABILITIES + EQUITY | B25: 236495 | C25: 252496 | D25: 244860 | E25: 243197 | F25: 252399 | G25: 260823
A26: KEY RATIOS
A27: Net Debt | B27: =B17-B5 -> 38556 | C27: =C17-C5 -> 27300 | D27: =D17-D5 -> 24347 | E27: =E17-E5 -> 30867 | F27: =F17-F5 -> 31974 | G27: =G17-G5 -> 30287
A28: Current Ratio | B28: =IF(B16=0,0,B9/B16) -> 0.79452372 | C28: =IF(C16=0,0,C9/C16) -> 0.97217335 | D28: =IF(D16=0,0,D9/D16) -> 0.9277973 | E28: =IF(E16=0,0,E9/E16) -> 0.82057095 | F28: =IF(F16=0,0,F9/F16) -> 0.83186712 | G28: =IF(G16=0,0,G9/G16) -> 0.82268285
A29: Debt / Equity | B29: =IF(B24=0,0,B17/B24) -> 0.58883902 | C29: =IF(C24=0,0,C17/C24) -> 0.51457198 | D29: =IF(D24=0,0,D17/D24) -> 0.42558031 | E29: =IF(E24=0,0,E17/E24) -> 0.47152375 | F29: =IF(F24=0,0,F17/F24) -> 0.46310418 | G29: =IF(G24=0,0,G17/G24) -> 0.40365014

Sheet Cash Flow Statement
A1: WALMART INC. (WMT) - Cash Flow Statement
A2: USD in millions | Fiscal Year Ends January 31 | Source: Macrotrends
A3: Metric | B3: FY2020 | C3: FY2021 | D3: FY2022 | E3: FY2023 | F3: FY2024 | G3: FY2025 | H3: FY2026 | I3: FY2027E | J3: FY2028E | K3: FY2029E | L3: FY2030E | M3: FY2031E
A4: OPERATING ACTIVITIES
A5: Net Income / Loss | B5: 15201 | C5: 13706 | D5: 13940 | E5: 11292 | F5: 16270 | G5: 20157 | H5: 22270 | I5: ='Income Statement'!I16 -> 25444.309 | J5: ='Income Statement'!J16 -> 28937.693 | K5: ='Income Statement'!K16 -> 32630.335 | L5: ='Income Statement'!L16 -> 36480.541 | M5: ='Income Statement'!M16 -> 40507.565
A6: D&A | B6: 10987 | C6: 11152 | D6: 10658 | E6: 10945 | F6: 11853 | G6: 12973 | H6: 14203 | I6: ='Income Statement'!I20 -> 14905.107 | J6: ='Income Statement'!J20 -> 15575.837 | K6: ='Income Statement'!K20 -> 16245.597 | L6: ='Income Statement'!L20 -> 16895.421 | M6: ='Income Statement'!M20 -> 17537.447
A7: Other Non-Cash Items | B7: -2587 | C7: 1723 | D7: 4528 | E7: 2132 | F7: 3018 | G7: 243 | H7: 261 | I7: =Assumptions!B17 -> 500 | J7: =Assumptions!C17 -> 500 | K7: =Assumptions!D17 -> 500 | L7: =Assumptions!E17 -> 500 | M7: =Assumptions!F17 -> 500
A8: Change in Accounts Receivable | B8: -368 | C8: -1086 | D8: -1796 | E8: 240 | F8: -797 | G8: -1106 | H8: -1136 | I8: ='Income Statement'!I4*Assumptions!B14 -> -1117.883 | J8: ='Income Statement'!J4*Assumptions!C14 -> -1168.1877 | K8: ='Income Statement'!K4*Assumptions!D14 -> -1218.4198 | L8: ='Income Statement'!L4*Assumptions!E14 -> -1267.1566 | M8: ='Income Statement'!M4*Assumptions!F14 -> -1315.3086
A9: Change in Inventory | B9: -1311 | C9: -2395 | D9: -11764 | E9: -528 | F9: 2017 | G9: -2755 | H9: -1443 | I9: ='Income Statement'!I4*Assumptions!B15 -> -1490.5107 | J9: ='Income Statement'!J4*Assumptions!C15 -> -1557.5837 | K9: ='Income Statement'!K4*Assumptions!D15 -> -1624.5597 | L9: ='Income Statement'!L4*Assumptions!E15 -> -1689.5421 | M9: ='Income Statement'!M4*Assumptions!F15 -> -1753.7447
A10: Change in Accounts Payable | B10: 1831 | C10: 6966 | D10: 5520 | E10: -1425 | F10: 2515 | G10: 3228 | H10: 1611 | I10: ='Income Statement'!I4*Assumptions!B16 -> 2981.0213 | J10: ='Income Statement'!J4*Assumptions!C16 -> 3115.1673 | K10: ='Income Statement'!K4*Assumptions!D16 -> 3249.1195 | L10: ='Income Statement'!L4*Assumptions!E16 -> 3379.0843 | M10: ='Income Statement'!M4*Assumptions!F16 -> 3507.4895
A11: Other Working Capital | B11: 295 | C11: 7972 | D11: -6597 | E11: 2553 | F11: 1943 | G11: 181 | H11: 752 | I11: =0 -> 0 | J11: =0 -> 0 | K11: =0 -> 0 | L11: =0 -> 0 | M11: =0 -> 0
A12: Cash Flow from Operations | B12: 25255 | C12: 36074 | D12: 24181 | E12: 28841 | F12: 35726 | G12: 36443 | H12: 41565 | I12: =SUM(I5:I11) -> 41222.043 | J12: =SUM(J5:J11) -> 45402.926 | K12: =SUM(K5:K11) -> 49782.072 | L12: =SUM(L5:L11) -> 54298.348 | M12: =SUM(M5:M11) -> 58983.449
A13: INVESTING ACTIVITIES
A14: Capital Expenditures (Capex) | B14: -10384 | C14: -10049 | D14: -12712 | E14: -16687 | F14: -20356 | G14: -23351 | H14: -26536 | I14: =-'Income Statement'!I4*Assumptions!B9 -> -27574.447 | J14: =-'Income Statement'!J4*Assumptions!C9 -> -28036.506 | K14: =-'Income Statement'!K4*Assumptions!D9 -> -27617.516 | L14: =-'Income Statement'!L4*Assumptions!E9 -> -27032.674 | M14: =-'Income Statement'!M4*Assumptions!F9 -> -26306.171
A15: Net Acquisitions/Divestitures | B15: 777 | C15: -124 | D15: 7576 | E15: -740 | F15: -9 | G15: 2184 | H15: -53 | I15: =0 -> 0 | J15: =0 -> 0 | K15: =0 -> 0 | L15: =0 -> 0 | M15: =0 -> 0
A16: Other Investing Activities | B16: 479 | C16: 102 | D16: -879 | E16: -295 | F16: -922 | G16: -212 | H16: -688 | I16: =0 -> 0 | J16: =0 -> 0 | K16: =0 -> 0 | L16: =0 -> 0 | M16: =0 -> 0
A17: Cash Flow from Investing | B17: -9128 | C17: -10071 | D17: -6015 | E17: -17722 | F17: -21287 | G17: -21379 | H17: -26350 | I17: =SUM(I14:I16) -> -27574.447 | J17: =SUM(J14:J16) -> -28036.506 | K17: =SUM(K14:K16) -> -27617.516 | L17: =SUM(L14:L16) -> -27032.674 | M17: =SUM(M14:M16) -> -26306.171
A18: FINANCING ACTIVITIES
A19: Net Debt Issuance/Repayment | B19: -1071 | C19: -5706 | D19: -5872 | E19: 2318 | F19: 1262 | G19: -1256 | H19: 4881 | I19: =0 -> 0 | J19: =0 -> 0 | K19: =0 -> 0 | L19: =0 -> 0 | M19: =0 -> 0
A20: Net Equity Issued/Repurchased | B20: -5665 | C20: -2485 | D20: -6548 | E20: -9854 | F20: -2063 | G20: -4132 | H20: -8088 | I20: =Assumptions!B19 -> -8000 | J20: =Assumptions!C19 -> -8000 | K20: =Assumptions!D19 -> -8000 | L20: =Assumptions!E19 -> -8000 | M20: =Assumptions!F19 -> -8000
A21: Dividends Paid | B21: -6603 | C21: -6550 | D21: -6576 | E21: -6558 | F21: -6903 | G21: -7264 | H21: -7507 | I21: =Assumptions!B18 -> -7700 | J21: =Assumptions!C18 -> -7930 | K21: =Assumptions!D18 -> -8165 | L21: =Assumptions!E18 -> -8410 | M21: =Assumptions!F18 -> -8660
A22: Other Financing Activities | B22: -960 | C22: -1376 | D22: -3832 | E22: -2945 | F22: -5710 | G22: -2170 | H22: -2839 | I22: =0 -> 0 | J22: =0 -> 0 | K22: =0 -> 0 | L22: =0 -> 0 | M22: =0 -> 0
A23: Cash Flow from Financing | B23: -14299 | C23: -16117 | D23: -22828 | E23: -17039 | F23: -13414 | G23: -14822 | H23: -13553 | I23: =SUM(I19:I22) -> -15700 | J23: =SUM(J19:J22) -> -15930 | K23: =SUM(K19:K22) -> -16165 | L23: =SUM(L19:L22) -> -16410 | M23: =SUM(M19:M22) -> -16660
A24: KEY METRICS
A25: Net Change in Cash | B25: 1759 | C25: -2954 | D25: -5993 | E25: 1094 | F25: -399 | G25: 1785 | I25: =I12+I17+I23 -> -2052.404 | J25: =J12+J17+J23 -> 1436.4202 | K25: =K12+K17+K23 -> 5999.5566 | L25: =L12+L17+L23 -> 10855.674 | M25: =M12+M17+M23 -> 16017.278
A26: Free Cash Flow (CFO - Capex) | B26: =B12+B14 -> 14871 | C26: =C12+C14 -> 26025 | D26: =D12+D14 -> 11469 | E26: =E12+E14 -> 12154 | F26: =F12+F14 -> 15370 | G26: =G12+G14 -> 13092 | H26: =H12+H14 -> 15029 | I26: =I12+I14 -> 13647.596 | ... M26: =M12+M14 -> 32677.278
A27: FCF Margin % | B27: =IF('Income Statement'!B4=0,0,B26/'Income Statement'!B4) -> 0.028381721 | C27: =IF('Income Statement'!C4=0,0,C26/'Income Statement'!C4) -> 0.046543778 | D27: =IF('Income Statement'!D4=0,0,D26/'Income Statement'!D4) -> 0.020024304 | E27: =IF('Income Statement'!E4=0,0,E26/'Income Statement'!E4) -> 0.019882576 | F27: =IF('Income Statement'!F4=0,0,F26/'Income Statement'!F4) -> 0.023714561 | G27: =IF('Income Statement'!G4=0,0,G26/'Income Statement'!G4) -> 0.019225093 | H27: =IF('Income Statement'!H4=0,0,H26/'Income Statement'!H4) -> 0.021073724 | I27: =IF('Income Statement'!I4=0,0,I26/'Income Statement'!I4) -> 0.018312645 | ... M27: =IF('Income Statement'!M4=0,0,M26/'Income Statement'!M4) -> 0.037265717
A28: Capex / Revenue % | B28: =IF('Income Statement'!B4=0,0,ABS(B14)/'Income Statement'!B4) -> 0.019818155 | C28: =IF('Income Statement'!C4=0,0,ABS(C14)/'Income Statement'!C4) -> 0.01797189 | D28: =IF('Income Statement'!D4=0,0,ABS(D14)/'Income Statement'!D4) -> 0.02219452 | E28: =IF('Income Statement'!E4=0,0,ABS(E14)/'Income Statement'!E4) -> 0.027298054 | F28: =IF('Income Statement'!F4=0,0,ABS(F14)/'Income Statement'!F4) -> 0.031407522 | G28: =IF('Income Statement'!G4=0,0,ABS(G14)/'Income Statement'!G4) -> 0.034290036 | H28: =IF('Income Statement'!H4=0,0,ABS(H14)/'Income Statement'!H4) -> 0.037208885 | I28: =IF('Income Statement'!I4=0,0,ABS(I14)/'Income Statement'!I4) -> 0.037 | ... M28: =IF('Income Statement'!M4=0,0,ABS(M14)/'Income Statement'!M4) -> 0.03

Sheet DCF Valuation
A1: WALMART INC. (WMT) - DCF Valuation
A2: USD in millions | Base Case | Fiscal Year Ends January 31
A4: KEY DCF ASSUMPTIONS
C5: FY2027E | D5: FY2028E | E5: FY2029E | F5: FY2030E | G5: FY2031E
A6: Free Cash Flow ($mm) | C6: ='Cash Flow Statement'!I26 -> 13647.596 | D6: ='Cash Flow Statement'!J26 -> 17366.42 | E6: ='Cash Flow Statement'!K26 -> 22164.557 | F6: ='Cash Flow Statement'!L26 -> 27265.674 | G6: ='Cash Flow Statement'!M26 -> 32677.278
A7: WACC (Discount Rate) | C7: 0.07 | D7: Applied uniformly across all projection years
A8: Terminal EV/EBITDA Exit Multiple | C8: 16 | D8: Discount to current ~18x; conservative base case
A9: FY2031E EBITDA ($mm) | C9: ='Income Statement'!M18 -> 71903.534
A10: Net Debt ($mm) [LT Debt minus Cash, FY2025] | C10: ='Balance Sheet'!G17-'Balance Sheet'!G5 -> 30287
A11: Shares Outstanding (mm) [FY2027E] | C11: =Assumptions!B11 -> 7950
A13: DISCOUNT THE FREE CASH FLOWS
C14: FY2027E | D14: FY2028E | E14: FY2029E | F14: FY2030E | G14: FY2031E | H14: Total
A15: Discount Period (Year) | C15: 1 | D15: 2 | E15: 3 | F15: 4 | G15: 5
A16: Discount Factor [ 1 / (1 + WACC)^Year ] | C16: =1/(1+$C7)^C15 -> 0.93457944 | D16: =1/(1+$C7)^D15 -> 0.87343873 | E16: =1/(1+$C7)^E15 -> 0.81629788 | F16: =1/(1+$C7)^F15 -> 0.76289521 | G16: =1/(1+$C7)^G15 -> 0.71298618
A17: PV of Free Cash Flow ($mm) | C17: =C6*C16 -> 12754.763 | D17: =D6*D16 -> 15168.504 | E17: =E6*E16 -> 18092.88 | F17: =F6*F16 -> 20800.852 | G17: =G6*G16 -> 23298.447 | H17: =SUM(C17:G17) -> 90115.447
A19: CALCULATE TERMINAL VALUE
A20: Terminal Value [ FY2031E EBITDA x Exit Multiple ] | C20: =C9*C8 -> 1150456.5
A21: PV of Terminal Value [ TV / (1 + WACC)^5 ] | C21: =C20/(1+C7)^5 -> 820259.62
A22: Terminal Value as % of Total EV | C22: =C21/(H17+C21) -> 0.90101284
A24: BRIDGE TO EQUITY VALUE AND PRICE TARGET
A25: Enterprise Value [ PV of FCFs + PV of Terminal Value ] | C25: =H17+C21 -> 910375.07
A26: Less: Net Debt | C26: =-C10 -> -30287
A27: Equity Value | C27: =C25+C26 -> 880088.07
A28: Divided by: Shares Outstanding (mm) | C28: =C11 -> 7950
A29: IMPLIED PRICE TARGET (DCF) | C29: =IF(C28=0,0,C27/C28) -> 110.7029
A32: SENSITIVITY ANALYSIS - Price Target by WACC and Exit Multiple
A33: Each cell shows the implied price target at that WACC / Exit Multiple combination.
A35: WACC \ Exit Multiple | B35: 13x | C35: 14x | D35: 15x | E35: 16x | F35: 17x | G35: 18x | H35: 19x
A36: 0.06 | B36: =IF(C11=0,0,(('Cash Flow Statement'!I26/(1+0.06)^1+'Cash Flow Statement'!J26/(1+0.06)^2+'Cash Flow Statement'!K26/(1+0.06)^3+'Cash Flow Statement'!L26/(1+0.06)^4+'Cash Flow Statement'!M26/(1+0.06)^5+('Income Statement'!M18*13)/(1+0.06)^5)-C10)/C11) -> 95.744127 | C36: =IF(C11=0,0,(('Cash Flow Statement'!I26/(1+0.06)^1+'Cash Flow Statement'!J26/(1+0.06)^2+'Cash Flow Statement'!K26/(1+0.06)^3+'Cash Flow Statement'!L26/(1+0.06)^4+'Cash Flow Statement'!M26/(1+0.06)^5+('Income Statement'!M18*14)/(1+0.06)^5)-C10)/C11) -> 102.50268 | D36: =IF(C11=0,0,(('Cash Flow Statement'!I26/(1+0.06)^1+'Cash Flow Statement'!J26/(1+0.06)^2+'Cash Flow Statement'!K26/(1+0.06)^3+'Cash Flow Statement'!L26/(1+0.06)^4+'Cash Flow Statement'!M26/(1+0.06)^5+('Income Statement'!M18*15)/(1+0.06)^5)-C10)/C11) -> 109.26123 | E36: =IF(C11=0,0,(('Cash Flow Statement'!I26/(1+0.06)^1+'Cash Flow Statement'!J26/(1+0.06)^2+'Cash Flow Statement'!K26/(1+0.06)^3+'Cash Flow Statement'!L26/(1+0.06)^4+'Cash Flow Statement'!M26/(1+0.06)^5+('Income Statement'!M18*16)/(1+0.06)^5)-C10)/C11) -> 116.01979 | F36: =IF(C11=0,0,(('Cash Flow Statement'!I26/(1+0.06)^1+'Cash Flow Statement'!J26/(1+0.06)^2+'Cash Flow Statement'!K26/(1+0.06)^3+'Cash Flow Statement'!L26/(1+0.06)^4+'Cash Flow Statement'!M26/(1+0.06)^5+('Income Statement'!M18*17)/(1+0.06)^5)-C10)/C11) -> 122.77834 | G36: =IF(C11=0,0,(('Cash Flow Statement'!I26/(1+0.06)^1+'Cash Flow Statement'!J26/(1+0.06)^2+'Cash Flow Statement'!K26/(1+0.06)^3+'Cash Flow Statement'!L26/(1+0.06)^4+'Cash Flow Statement'!M26/(1+0.06)^5+('Income Statement'!M18*18)/(1+0.06)^5)-C10)/C11) -> 129.5369 | H36: =IF(C11=0,0,(('Cash Flow Statement'!I26/(1+0.06)^1+'Cash Flow Statement'!J26/(1+0.06)^2+'Cash Flow Statement'!K26/(1+0.06)^3+'Cash Flow Statement'!L26/(1+0.06)^4+'Cash Flow Statement'!M26/(1+0.06)^5+('Income Statement'!M18*19)/(1+0.06)^5)-C10)/C11) -> 136.29545
A37: 0.065 | B37: =IF(C11=0,0,(('Cash Flow Statement'!I26/(1+0.065)^1+'Cash Flow Statement'!J26/(1+0.065)^2+'Cash Flow Statement'!K26/(1+0.065)^3+'Cash Flow Statement'!L26/(1+0.065)^4+'Cash Flow Statement'!M26/(1+0.065)^5+('Income Statement'!M18*13)/(1+0.065)^5)-C10)/C11) -> 93.520217 | C37: =IF(C11=0,0,(('Cash Flow Statement'!I26/(1+0.065)^1+'Cash Flow Statement'!J26/(1+0.065)^2+'Cash Flow Statement'!K26/(1+0.065)^3+'Cash Flow Statement'!L26/(1+0.065)^4+'Cash Flow Statement'!M26/(1+0.065)^5+('Income Statement'!M18*14)/(1+0.065)^5)-C10)/C11) -> 100.1216 | D37: =IF(C11=0,0,(('Cash Flow Statement'!I26/(1+0.065)^1+'Cash Flow Statement'!J26/(1+0.065)^2+'Cash Flow Statement'!K26/(1+0.065)^3+'Cash Flow Statement'!L26/(1+0.065)^4+'Cash Flow Statement'!M26/(1+0.065)^5+('Income Statement'!M18*15)/(1+0.065)^5)-C10)/C11) -> 106.72299 | E37: =IF(C11=0,0,(('Cash Flow Statement'!I26/(1+0.065)^1+'Cash Flow Statement'!J26/(1+0.065)^2+'Cash Flow Statement'!K26/(1+0.065)^3+'Cash Flow Statement'!L26/(1+0.065)^4+'Cash Flow Statement'!M26/(1+0.065)^5+('Income Statement'!M18*16)/(1+0.065)^5)-C10)/C11) -> 113.32437 | F37: =IF(C11=0,0,(('Cash Flow Statement'!I26/(1+0.065)^1+'Cash Flow Statement'!J26/(1+0.065)^2+'Cash Flow Statement'!K26/(1+0.065)^3+'Cash Flow Statement'!L26/(1+0.065)^4+'Cash Flow Statement'!M26/(1+0.065)^5+('Income Statement'!M18*17)/(1+0.065)^5)-C10)/C11) -> 119.92576 | G37: =IF(C11=0,0,(('Cash Flow Statement'!I26/(1+0.065)^1+'Cash Flow Statement'!J26/(1+0.065)^2+'Cash Flow Statement'!K26/(1+0.065)^3+'Cash Flow Statement'!L26/(1+0.065)^4+'Cash Flow Statement'!M26/(1+0.065)^5+('Income Statement'!M18*18)/(1+0.065)^5)-C10)/C11) -> 126.52714 | H37: =IF(C11=0,0,(('Cash Flow Statement'!I26/(1+0.065)^1+'Cash Flow Statement'!J26/(1+0.065)^2+'Cash Flow Statement'!K26/(1+0.065)^3+'Cash Flow Statement'!L26/(1+0.065)^4+'Cash Flow Statement'!M26/(1+0.065)^5+('Income Statement'!M18*19)/(1+0.065)^5)-C10)/C11) -> 133.12853
A38: 0.07 | B38: =IF(C11=0,0,(('Cash Flow Statement'!I26/(1+0.07)^1+'Cash Flow Statement'!J26/(1+0.07)^2+'Cash Flow Statement'!K26/(1+0.07)^3+'Cash Flow Statement'!L26/(1+0.07)^4+'Cash Flow Statement'!M26/(1+0.07)^5+('Income Statement'!M18*13)/(1+0.07)^5)-C10)/C11) -> 91.357156 | C38: =IF(C11=0,0,(('Cash Flow Statement'!I26/(1+0.07)^1+'Cash Flow Statement'!J26/(1+0.07)^2+'Cash Flow Statement'!K26/(1+0.07)^3+'Cash Flow Statement'!L26/(1+0.07)^4+'Cash Flow Statement'!M26/(1+0.07)^5+('Income Statement'!M18*14)/(1+0.07)^5)-C10)/C11) -> 97.805738 | D38: =IF(C11=0,0,(('Cash Flow Statement'!I26/(1+0.07)^1+'Cash Flow Statement'!J26/(1+0.07)^2+'Cash Flow Statement'!K26/(1+0.07)^3+'Cash Flow Statement'!L26/(1+0.07)^4+'Cash Flow Statement'!M26/(1+0.07)^5+('Income Statement'!M18*15)/(1+0.07)^5)-C10)/C11) -> 104.25432 | E38: =IF(C11=0,0,(('Cash Flow Statement'!I26/(1+0.07)^1+'Cash Flow Statement'!J26/(1+0.07)^2+'Cash Flow Statement'!K26/(1+0.07)^3+'Cash Flow Statement'!L26/(1+0.07)^4+'Cash Flow Statement'!M26/(1+0.07)^5+('Income Statement'!M18*16)/(1+0.07)^5)-C10)/C11) -> 110.7029 | F38: =IF(C11=0,0,(('Cash Flow Statement'!I26/(1+0.07)^1+'Cash Flow Statement'!J26/(1+0.07)^2+'Cash Flow Statement'!K26/(1+0.07)^3+'Cash Flow Statement'!L26/(1+0.07)^4+'Cash Flow Statement'!M26/(1+0.07)^5+('Income Statement'!M18*17)/(1+0.07)^5)-C10)/C11) -> 117.15148 | G38: =IF(C11=0,0,(('Cash Flow Statement'!I26/(1+0.07)^1+'Cash Flow Statement'!J26/(1+0.07)^2+'Cash Flow Statement'!K26/(1+0.07)^3+'Cash Flow Statement'!L26/(1+0.07)^4+'Cash Flow Statement'!M26/(1+0.07)^5+('Income Statement'!M18*18)/(1+0.07)^5)-C10)/C11) -> 123.60007 | H38: =IF(C11=0,0,(('Cash Flow Statement'!I26/(1+0.07)^1+'Cash Flow Statement'!J26/(1+0.07)^2+'Cash Flow Statement'!K26/(1+0.07)^3+'Cash Flow Statement'!L26/(1+0.07)^4+'Cash Flow Statement'!M26/(1+0.07)^5+('Income Statement'!M18*19)/(1+0.07)^5)-C10)/C11) -> 130.04865
A39: 0.075 | B39: =IF(C11=0,0,(('Cash Flow Statement'!I26/(1+0.075)^1+'Cash Flow Statement'!J26/(1+0.075)^2+'Cash Flow Statement'!K26/(1+0.075)^3+'Cash Flow Statement'!L26/(1+0.075)^4+'Cash Flow Statement'!M26/(1+0.075)^5+('Income Statement'!M18*13)/(1+0.075)^5)-C10)/C11) -> 89.252995 | C39: =IF(C11=0,0,(('Cash Flow Statement'!I26/(1+0.075)^1+'Cash Flow Statement'!J26/(1+0.075)^2+'Cash Flow Statement'!K26/(1+0.075)^3+'Cash Flow Statement'!L26/(1+0.075)^4+'Cash Flow Statement'!M26/(1+0.075)^5+('Income Statement'!M18*14)/(1+0.075)^5)-C10)/C11) -> 95.552998 | D39: =IF(C11=0,0,(('Cash Flow Statement'!I26/(1+0.075)^1+'Cash Flow Statement'!J26/(1+0.075)^2+'Cash Flow Statement'!K26/(1+0.075)^3+'Cash Flow Statement'!L26/(1+0.075)^4+'Cash Flow Statement'!M26/(1+0.075)^5+('Income Statement'!M18*15)/(1+0.075)^5)-C10)/C11) -> 101.853 | E39: =IF(C11=0,0,(('Cash Flow Statement'!I26/(1+0.075)^1+'Cash Flow Statement'!J26/(1+0.075)^2+'Cash Flow Statement'!K26/(1+0.075)^3+'Cash Flow Statement'!L26/(1+0.075)^4+'Cash Flow Statement'!M26/(1+0.075)^5+('Income Statement'!M18*16)/(1+0.075)^5)-C10)/C11) -> 108.15301 | F39: =IF(C11=0,0,(('Cash Flow Statement'!I26/(1+0.075)^1+'Cash Flow Statement'!J26/(1+0.075)^2+'Cash Flow Statement'!K26/(1+0.075)^3+'Cash Flow Statement'!L26/(1+0.075)^4+'Cash Flow Statement'!M26/(1+0.075)^5+('Income Statement'!M18*17)/(1+0.075)^5)-C10)/C11) -> 114.45301 | G39: =IF(C11=0,0,(('Cash Flow Statement'!I26/(1+0.075)^1+'Cash Flow Statement'!J26/(1+0.075)^2+'Cash Flow Statement'!K26/(1+0.075)^3+'Cash Flow Statement'!L26/(1+0.075)^4+'Cash Flow Statement'!M26/(1+0.075)^5+('Income Statement'!M18*18)/(1+0.075)^5)-C10)/C11) -> 120.75301 | H39: =IF(C11=0,0,(('Cash Flow Statement'!I26/(1+0.075)^1+'Cash Flow Statement'!J26/(1+0.075)^2+'Cash Flow Statement'!K26/(1+0.075)^3+'Cash Flow Statement'!L26/(1+0.075)^4+'Cash Flow Statement'!M26/(1+0.075)^5+('Income Statement'!M18*19)/(1+0.075)^5)-C10)/C11) -> 127.05302
A40: 0.08 | B40: =IF(C11=0,0,(('Cash Flow Statement'!I26/(1+0.08)^1+'Cash Flow Statement'!J26/(1+0.08)^2+'Cash Flow Statement'!K26/(1+0.08)^3+'Cash Flow Statement'!L26/(1+0.08)^4+'Cash Flow Statement'!M26/(1+0.08)^5+('Income Statement'!M18*13)/(1+0.08)^5)-C10)/C11) -> 87.20586 | C40: =IF(C11=0,0,(('Cash Flow Statement'!I26/(1+0.08)^1+'Cash Flow Statement'!J26/(1+0.08)^2+'Cash Flow Statement'!K26/(1+0.08)^3+'Cash Flow Statement'!L26/(1+0.08)^4+'Cash Flow Statement'!M26/(1+0.08)^5+('Income Statement'!M18*14)/(1+0.08)^5)-C10)/C11) -> 93.361374 | D40: =IF(C11=0,0,(('Cash Flow Statement'!I26/(1+0.08)^1+'Cash Flow Statement'!J26/(1+0.08)^2+'Cash Flow Statement'!K26/(1+0.08)^3+'Cash Flow Statement'!L26/(1+0.08)^4+'Cash Flow Statement'!M26/(1+0.08)^5+('Income Statement'!M18*15)/(1+0.08)^5)-C10)/C11) -> 99.516888 | E40: =IF(C11=0,0,(('Cash Flow Statement'!I26/(1+0.08)^1+'Cash Flow Statement'!J26/(1+0.08)^2+'Cash Flow Statement'!K26/(1+0.08)^3+'Cash Flow Statement'!L26/(1+0.08)^4+'Cash Flow Statement'!M26/(1+0.08)^5+('Income Statement'!M18*16)/(1+0.08)^5)-C10)/C11) -> 105.6724 | F40: =IF(C11=0,0,(('Cash Flow Statement'!I26/(1+0.08)^1+'Cash Flow Statement'!J26/(1+0.08)^2+'Cash Flow Statement'!K26/(1+0.08)^3+'Cash Flow Statement'!L26/(1+0.08)^4+'Cash Flow Statement'!M26/(1+0.08)^5+('Income Statement'!M18*17)/(1+0.08)^5)-C10)/C11) -> 111.82792 | G40: =IF(C11=0,0,(('Cash Flow Statement'!I26/(1+0.08)^1+'Cash Flow Statement'!J26/(1+0.08)^2+'Cash Flow Statement'!K26/(1+0.08)^3+'Cash Flow Statement'!L26/(1+0.08)^4+'Cash Flow Statement'!M26/(1+0.08)^5+('Income Statement'!M18*18)/(1+0.08)^5)-C10)/C11) -> 117.98343 | H40: =IF(C11=0,0,(('Cash Flow Statement'!I26/(1+0.08)^1+'Cash Flow Statement'!J26/(1+0.08)^2+'Cash Flow Statement'!K26/(1+0.08)^3+'Cash Flow Statement'!L26/(1+0.08)^4+'Cash Flow Statement'!M26/(1+0.08)^5+('Income Statement'!M18*19)/(1+0.08)^5)-C10)/C11) -> 124.13894
A42: Yellow = Base case | Green = Bull scenario | White = Bear scenario

Sheet Trading Comps
A1: WALMART INC. (WMT) - Trading Comparables
A2: LTM = Last Twelve Months | Figures in USD millions unless noted | Prices as of April 2026 (verify before use)
A3: NOTE: Comp figures are approximate estimates. Verify current market data before presenting this analysis.
A5: PEER GROUP SELECTION RATIONALE
A6: Amazon (AMZN) | B6: Most direct competitor. Retail + ads + fulfillment. Key benchmark for Walmart's ecosystem ambitions.
A7: Costco (COST) | B7: Membership model comp. High loyalty, strong traffic. Relevant for Walmart+ thesis.
A8: Target (TGT) | B8: Direct mass merchandise peer. Similar customer demographic. No membership moat.
A9: Kroger (KR) | B9: Grocery-heavy peer. Tests whether WMT deserves premium to pure grocery.
A10: Dollar General (DG) | B10: Value retail comp. Relevant for low-income consumer exposure and pricing power debate.
A12: TRADING COMPARABLES
A13: Company | B13: Ticker | C13: Mkt Cap ($B) | D13: Net Debt ($mm) | E13: EV ($mm) | F13: LTM Rev ($mm) | G13: LTM EBITDA | H13: EV/ Revenue | I13: EV/ EBITDA | J13: P/E (NTM) | K13: EBITDA Margin
A14: Amazon | B14: AMZN | C14: 2100 | D14: -60000 | E14: 2040000 | F14: 638000 | G14: 118000 | H14: =IF(F14=0,0,E14/F14) -> 3.1974922 | I14: =IF(G14=0,0,E14/G14) -> 17.288136 | J14: 38 | K14: =IF(F14=0,0,G14/F14) -> 0.18495298
A15: Costco | B15: COST | C15: 370 | D15: 3000 | E15: 373000 | F15: 245000 | G15: 10200 | H15: =IF(F15=0,0,E15/F15) -> 1.522449 | I15: =IF(G15=0,0,E15/G15) -> 36.568627 | J15: 50 | K15: =IF(F15=0,0,G15/F15) -> 0.041632653
A16: Target | B16: TGT | C16: 53 | D16: 14000 | E16: 67000 | F16: 107000 | G16: 6800 | H16: =IF(F16=0,0,E16/F16) -> 0.62616822 | I16: =IF(G16=0,0,E16/G16) -> 9.8529412 | J16: 18 | K16: =IF(F16=0,0,G16/F16) -> 0.063551402
A17: Kroger | B17: KR | C17: 42 | D17: 11000 | E17: 53000 | F17: 150000 | G17: 7000 | H17: =IF(F17=0,0,E17/F17) -> 0.35333333 | I17: =IF(G17=0,0,E17/G17) -> 7.5714286 | J17: 17 | K17: =IF(F17=0,0,G17/F17) -> 0.046666667
A18: Dollar General | B18: DG | C18: 24 | D18: 6500 | E18: 30500 | F18: 40000 | G18: 3100 | H18: =IF(F18=0,0,E18/F18) -> 0.7625 | I18: =IF(G18=0,0,E18/G18) -> 9.8387097 | J18: 23 | K18: =IF(F18=0,0,G18/F18) -> 0.0775
A19: Median (Peers) | C19: =MEDIAN(C14:C18) -> 53 | D19: =MEDIAN(D14:D18) -> 6500 | E19: =MEDIAN(E14:E18) -> 67000 | F19: =MEDIAN(F14:F18) -> 150000 | G19: =MEDIAN(G14:G18) -> 7000 | H19: =MEDIAN(H14:H18) -> 0.7625 | I19: =MEDIAN(I14:I18) -> 9.8529412 | J19: =MEDIAN(J14:J18) -> 23 | K19: =MEDIAN(K14:K18) -> 0.063551402
A20: Walmart (WMT) - Subject | B20: WMT | C20: 762.09 | D20: 30287 | E20: =C20*1000+D20 -> 792377 | F20: 713163 | G20: 44028 | H20: =IF(F20=0,0,E20/F20) -> 1.1110742 | I20: =IF(G20=0,0,E20/G20) -> 17.997115 | J20: =IF(21893=0,0,C20*1000/21893) -> 34.809757 | K20: =IF(F20=0,0,G20/F20) -> 0.061736237
A22: IMPLIED PRICE TARGET FROM COMPS
B23: Method | C23: Multiple Used | D23: Applied to (FY2027E) | E23: Implied EV ($mm) | F23: Less: Net Debt | G23: Equity Value | H23: Shares (mm) | I23: Implied Price | J23: Weight | K23: Wtd Price
B24: EV / EBITDA | C24: =I19 -> 9.8529412 | D24: ='Income Statement'!I18 -> 49186.852 | E24: =C24*D24 -> 484635.16 | F24: =D20 -> 30287 | G24: =E24-F24 -> 454348.16 | H24: ='Income Statement'!I21 -> 7950 | I24: =IF(H24=0,0,G24/H24) -> 57.150712 | J24: 0.5 | K24: =I24*J24 -> 28.575356
B25: P / E (NTM) | C25: =J19 -> 23 | D25: ='Income Statement'!I16/'Income Statement'!I21 -> 3.200542 | E25: N/A (P/E applied to EPS directly) | I25: =C25*D25 -> 73.612466 | J25: 0.5 | K25: =I25*J25 -> 36.806233
A26: IMPLIED PRICE TARGET (COMPS) | I26: =K24+K25 -> 65.381589
A28: FINAL BLENDED PRICE TARGET
A29: Method | B29: Implied Price | C29: Weight | D29: Contribution
A30: DCF Valuation | B30: ='DCF Valuation'!C29 -> 110.7029 | C30: 0.7 | D30: =B30*C30 -> 77.492031
A31: Trading Comps | B31: =I26 -> 65.381589 | C31: 0.3 | D31: =B31*C31 -> 19.614477
A32: BLENDED PRICE TARGET | B32: =D30+D31 -> 97.106508 | C32: 70% DCF / 30% Comps
A33: RATING | B33: OVERWEIGHT | C33: Blended target implies ~2% upside from current price of $95. Variant view on margin expansion is not priced in by consensus.

Sheet Assumptions
A1: PROJECTION ASSUMPTIONS
A2: All projection drivers will be found here. Each assumption links into the IS / BS / CF projection columns.
A4: Driver | B4: FY2027E | C4: FY2028E | D4: FY2029E | E4: FY2030E | F4: FY2031E | G4: Notes
A5: Revenue Growth % | B5: 0.045 | C5: 0.045 | D5: 0.043 | E5: 0.04 | F5: 0.038 | G5: Key driver: separate retail vs. ads vs. membership
A6: Gross Margin % | B6: 0.251 | C6: 0.253 | D6: 0.255 | E6: 0.257 | F6: 0.259 | G6: Watch COGS inflation vs. mix shift to higher-margin revenue
A7: SG&A % of Revenue | B7: 0.205 | C7: 0.203 | D7: 0.201 | E7: 0.199 | F7: 0.197 | G7: Leverage expected as fixed cost base grows slower than rev
A8: EBITDA Margin % | B8: ='Income Statement'!I19 -> 0.066 | C8: ='Income Statement'!J19 -> 0.07 | D8: ='Income Statement'!K19 -> 0.074 | E8: ='Income Statement'!L19 -> 0.078 | F8: ='Income Statement'!M19 -> 0.082 | G8: Variant view: consensus underestimates by ~50-80bps by FY2029
A9: Capex % of Revenue | B9: 0.037 | C9: 0.036 | D9: 0.034 | E9: 0.032 | F9: 0.03 | G9: Rising due to fulfillment buildout; watch this closely
A10: Effective Tax Rate | B10: 0.25 | C10: 0.25 | D10: 0.25 | E10: 0.25 | F10: 0.25 | G10: Use historical avg ~24-25%
A11: Shares Outstanding | B11: 7950 | C11: 7880 | D11: 7810 | E11: 7740 | F11: 7670 | G11: Declining due to buybacks; use trend
A12: D&A % of Revenue | B12: 0.02 | C12: 0.02 | D12: 0.02 | E12: 0.02 | F12: 0.02 | G12: Project at 2.0% of revenue (consistent with FY2024-FY2026 avg)
A13: Non-Operating Inc/Exp ($mm) | B13: -356 | C13: -356 | D13: -356 | E13: -356 | F13: -356 | G13: Reflects net interest expense; held flat at FY2026 level
A14: Change in AR (% of Rev) | B14: -0.0015 | C14: -0.0015 | D14: -0.0015 | E14: -0.0015 | F14: -0.0015 | G14: Working capital: AR grows with revenue
A15: Change in Inventory (% of Rev) | B15: -0.002 | C15: -0.002 | D15: -0.002 | E15: -0.002 | F15: -0.002 | G15: Working capital: inventory grows with revenue
A16: Change in AP (% of Rev) | B16: 0.004 | C16: 0.004 | D16: 0.004 | E16: 0.004 | F16: 0.004 | G16: Working capital: payables grow with revenue
A17: Other Non-Cash Items ($mm) | B17: 500 | C17: 500 | D17: 500 | E17: 500 | F17: 500 | G17: Held near FY2026 level; catch-all non-cash
A18: Dividends Paid ($mm) | B18: -7700 | C18: -7930 | D18: -8165 | E18: -8410 | F18: -8660 | G18: 3% annual growth from FY2026 base
A19: Net Buybacks ($mm) | B19: -8000 | C19: -8000 | D19: -8000 | E19: -8000 | F19: -8000 | G19: Held at recent avg; reduces share count
